streamlit_chat_widget/__init__.py
streamlit_chat_widget/frontend/build/asset-manifest.json
streamlit_chat_widget/frontend/build/bootstrap.min.css
streamlit_chat_widget/frontend/build/index.html
streamlit_chat_widget/frontend/build/static/css/main.be80bdc5.css
streamlit_chat_widget/frontend/build/static/css/main.be80bdc5.css.map
streamlit_chat_widget/frontend/build/static/js/main.9ea47d06.js
streamlit_chat_widget/frontend/build/static/js/main.9ea47d06.js.LICENSE.txt
streamlit_chat_widget/frontend/build/static/js/main.9ea47d06.js.map
streamlit_chat_widget_tiangong-0.0.3.dist-info/LICENSE
streamlit_chat_widget_tiangong-0.0.3.dist-info/METADATA
streamlit_chat_widget_tiangong-0.0.3.dist-info/WHEEL
streamlit_chat_widget_tiangong-0.0.3.dist-info/top_level.txt
streamlit_chat_widget_tiangong-0.0.3.dist-info/RECORD
