Metadata-Version: 2.1
Name: streamlit_chat_widget_tiangong
Version: 0.0.3
Summary: A custom chat input widget for Streamlit based on Mohammed Bahageel's Chat Input Widget project
Home-page: https://github.com/linancn/Chat_input_widget
Author: Nan LI
Author-email: linanenv@gmail.com
Classifier: Programming Language :: Python :: 3
Classifier: License :: OSI Approved :: MIT License
Classifier: Operating System :: OS Independent
Requires-Python: >=3.6
License-File: LICENSE
Requires-Dist: streamlit>=1.0
